pyopenfec/__init__.py
pyopenfec/aggregates.py
pyopenfec/candidate.py
pyopenfec/committee.py
pyopenfec/filing.py
pyopenfec/report.py
pyopenfec/transaction.py
pyopenfec/utils.py
pyopenfec-0.2.5.dist-info/LICENSE.txt
pyopenfec-0.2.5.dist-info/WHEEL
pyopenfec-0.2.5.dist-info/METADATA
pyopenfec-0.2.5.dist-info/RECORD
