Metadata-Version: 2.1
Name: pyopenfec
Version: 0.2.5
Summary: OpenFEC API Client
Home-page: https://github.com/jeremyjbowers/pyopenfec
License: MIT
Keywords: fec,campaign,finance,openfec
Author: Jeremy Bowers
Author-email: jeremyjbowers@gmail.com
Requires-Python: >=3.5,<4.0
Classifier: License :: OSI Approved :: MIT License
Classifier: Programming Language :: Python :: 3
Classifier: Programming Language :: Python :: 3.5
Classifier: Programming Language :: Python :: 3.6
Classifier: Programming Language :: Python :: 3.7
Requires-Dist: pytz (>=2019.3,<2020.0)
Requires-Dist: requests (>=2.22,<3.0)
Project-URL: Repository, https://github.com/jeremyjbowers/pyopenfec
